[{"judgeId": 7270169, "judgeType": 1, "userId": "mentai8810graund", "problemId": "ITP2_1_A", "submissionDate": 1672387692594, "language": "C++", "status": 4, "cpuTime": 15, "memory": 3896, "codeSize": 406, "accuracy": "14/14", "judgeDate": 1672387693495, "score": 100, "problemTitle": null, "token": null}, {"judgeId": 7275626, "judgeType": 1, "userId": "mentai8810graund", "problemId": "ITP2_1_A", "submissionDate": 1672495981748, "language": "C++", "status": 4, "cpuTime": 16, "memory": 3912, "codeSize": 407, "accuracy": "14/14", "judgeDate": 1672495982670, "score": 100, "problemTitle": null, "token": null}]